reed/__init__.py
reed-0.0.4.dist-info/LICENSE
reed-0.0.4.dist-info/METADATA
reed-0.0.4.dist-info/WHEEL
reed-0.0.4.dist-info/top_level.txt
reed-0.0.4.dist-info/RECORD
