Metadata-Version: 2.1
Name: reed
Version: 0.0.4
Summary: Search for jobs using the Reed API in python.
Home-page: https://github.com/theo-r/reed
Author: Theo Rutter
Author-email: theo.rutter@gmail.com
License: UNKNOWN
Platform: UNKNOWN
Classifier: Programming Language :: Python :: 3
Classifier: License :: OSI Approved :: MIT License
Classifier: Operating System :: OS Independent
Requires-Python: >=3.6
